{
  "favicon": "images/favicon.ico",
  "background": "images/background.jpg",
  "icon": "images/eight.png",
  "title": "Mario Kart 8 Deluxe Course Sorter",
  "subTitle": "Rank the Booster Pass Wave 4 courses by comparing pairs of courses",
  "navigation": [
    {"text": "Original", "url": "/"},
    {"text": "Booster Wave 1", "data": "booster1.json"},
    {"text": "Booster Wave 2", "data": "booster2.json"},
    {"text": "Booster Wave 3", "data": "booster3.json"},
    {"text": "Booster Wave 4"},
    {"text": "Booster Waves 1-4", "data": "booster1-4.json"}
  ],
  "options": [
    {"title": "Amsterdam Drift",    "subTitle": "Fruit Cup",     "image": "images/booster/courses/fruit1.jpg",     "icon": "images/booster/cups/fruit.png"},
    {"title": "Riverside Park",     "subTitle": "Fruit Cup",     "image": "images/booster/courses/fruit2.jpg",     "icon": "images/booster/cups/fruit.png"},
    {"title": "DK Summit",          "subTitle": "Fruit Cup",     "image": "images/booster/courses/fruit3.jpg",     "icon": "images/booster/cups/fruit.png"},
    {"title": "Yoshi's Island",     "subTitle": "Fruit Cup",     "image": "images/booster/courses/fruit4.jpg",     "icon": "images/booster/cups/fruit.png"},
    {"title": "Bangkok Rush",       "subTitle": "Boomerang Cup", "image": "images/booster/courses/boomerang1.jpg", "icon": "images/booster/cups/boomerang.png"},
    {"title": "Mario Circuit",      "subTitle": "Boomerang Cup", "image": "images/booster/courses/boomerang2.jpg", "icon": "images/booster/cups/boomerang.png"},
    {"title": "Waluigi Stadium",    "subTitle": "Boomerang Cup", "image": "images/booster/courses/boomerang3.jpg", "icon": "images/booster/cups/boomerang.png"},
    {"title": "Singapore Speedway", "subTitle": "Boomerang Cup", "image": "images/booster/courses/boomerang4.jpg", "icon": "images/booster/cups/boomerang.png"}
  ]
}